openstd_spider/__init__.py
openstd_spider/__main__.py
openstd_spider/captcha.py
openstd_spider/cli.py
openstd_spider/exception.py
openstd_spider/pdf.py
openstd_spider/request.py
openstd_spider/schema.py
openstd_spider/utils.py
openstd_spider/parse/gb688.py
openstd_spider/parse/openstd.py
openstd_spider-0.0.1.dist-info/LICENSE
openstd_spider-0.0.1.dist-info/METADATA
openstd_spider-0.0.1.dist-info/WHEEL
openstd_spider-0.0.1.dist-info/entry_points.txt
openstd_spider-0.0.1.dist-info/top_level.txt
openstd_spider-0.0.1.dist-info/RECORD
