Metadata-Version: 2.2
Name: openstd_spider
Version: 0.0.1
Summary: 国家标准全文公开系统下载工具
Author-email: SocialSisterYi <1440239038@qq.com>
License: GPLV3
Project-URL: Repository, https://github.com/SocialSisterYi/OpenSTD_Spider
Requires-Python: <3.13,>=3.10
License-File: LICENSE
Requires-Dist: httpx>=0.28.1
Requires-Dist: opencv-python>=4.11.0.86
Requires-Dist: numpy>=2.2.3
Requires-Dist: beautifulsoup4>=4.13.3
Requires-Dist: ddddocr>=1.5.6
Requires-Dist: lxml>=5.3.1
Requires-Dist: reportlab>=4.3.1
Requires-Dist: typer>=0.15.1
Requires-Dist: rich>=13.9.4
Requires-Dist: dataclasses-json>=0.6.7
